df_squeezer
