Metadata-Version: 2.1
Name: df-squeezer
Version: 0.0.12
Summary: A small package to optimize memory usage of Pandas DataFrames
Home-page: https://github.com/dscients/squeezer
Author: Perttu Isotalo, Kenneth Breugelmans
Author-email: perttu.isotalo@gmail.com, kennethbreugelmans@gmail.com
Classifier: Programming Language :: Python :: 3
Classifier: License :: OSI Approved :: Apache Software License
Classifier: Operating System :: OS Independent
Requires-Python: >=3.9
